folds/__init__.py
folds/exceptions.py
folds/py.typed
folds/utils.py
folds/admin/__init__.py
folds/admin/admin.py
folds/app/__init__.py
folds/app/app.py
folds/app/bot.py
folds/app/bot_client.py
folds/app/bot_in_app.py
folds/app/skill.py
folds/context/__init__.py
folds/context/context_var_wrapper.py
folds/context/vars.py
folds/reload/__init__.py
folds/reload/__main__.py
folds/reload/watcher.py
folds/rules/__init__.py
folds/rules/parameter_types.py
folds/rules/rule.py
folds/rules/rule_builder_factory.py
folds/rules/rule_builder_set.py
folds-0.1.0.dist-info/METADATA
folds-0.1.0.dist-info/WHEEL
folds-0.1.0.dist-info/RECORD
