Metadata-Version: 2.4
Name: folds
Version: 0.1.0
Summary: An elegant and scalable framework for Telegram bots, based on Telethon
Author-email: Artem Ivanov <tmat.ivanov@gmail.com>
License-Expression: MIT
Requires-Python: >=3.12
Requires-Dist: telethon~=1.39.0
Requires-Dist: watchfiles~=1.0.4
